Missing_Values_101703291/Missing_Values_101703291.py
Missing_Values_101703291/__init__.py
Missing_Values_101703291-0.9.dist-info/METADATA
Missing_Values_101703291-0.9.dist-info/WHEEL
Missing_Values_101703291-0.9.dist-info/entry_points.txt
Missing_Values_101703291-0.9.dist-info/top_level.txt
Missing_Values_101703291-0.9.dist-info/RECORD
