Metadata-Version: 2.1
Name: Missing-Values-101703291
Version: 0.9
Summary: Python Package to find missing values in a dataset
Home-page: UNKNOWN
Author: Krishang Dubey
Author-email: kdubey1999@gmail.com
License: UNKNOWN
Platform: UNKNOWN
Classifier: Programming Language :: Python :: 3
Classifier: License :: OSI Approved :: MIT License
Classifier: Operating System :: OS Independent
Requires-Python: >=3.6
